MANIFEST.in
README.rst
setup.py
zcbot_predict_sdk/__init__.py
zcbot_predict_sdk/client.py
zcbot_predict_sdk/monitor.py
zcbot_predict_sdk.egg-info/PKG-INFO
zcbot_predict_sdk.egg-info/SOURCES.txt
zcbot_predict_sdk.egg-info/dependency_links.txt
zcbot_predict_sdk.egg-info/requires.txt
zcbot_predict_sdk.egg-info/top_level.txt
zcbot_predict_sdk/common/__init__.py
zcbot_predict_sdk/common/decator.py
zcbot_predict_sdk/common/exceptions.py
zcbot_predict_sdk/common/keys.py
zcbot_predict_sdk/common/thread_pool.py
zcbot_predict_sdk/common/utils.py
zcbot_predict_sdk/model/__init__.py
zcbot_predict_sdk/model/callback.py
zcbot_predict_sdk/model/param.py
zcbot_predict_sdk/model/response.py
zcbot_predict_sdk/service/__init__.py
zcbot_predict_sdk/service/base.py
zcbot_predict_sdk/service/info_extract.py
zcbot_predict_sdk/service/named_entity.py
zcbot_predict_sdk/service/sku_tag.py